jiki/__init__.py
jiki/cli.py
jiki/logging.py
jiki/mcp_client.py
jiki/orchestrator.py
jiki/sampling.py
jiki/tool_client.py
jiki/models/__init__.py
jiki/models/litellm.py
jiki/models/response.py
jiki/models/state.py
jiki/prompts/__init__.py
jiki/prompts/prompt_builder.py
jiki/prompts/utils.py
jiki/resources/__init__.py
jiki/resources/resource_manager.py
jiki/roots/__init__.py
jiki/roots/conversation_root_manager.py
jiki/roots/root_manager.py
jiki/serialization/__init__.py
jiki/serialization/helpers.py
jiki/tools/__init__.py
jiki/tools/config.py
jiki/tools/tool.py
jiki/transports/factory.py
jiki/utils/__init__.py
jiki/utils/cleaning.py
jiki/utils/context.py
jiki/utils/logging.py
jiki/utils/parsing.py
jiki/utils/streaming.py
jiki/utils/token.py
jiki/utils/tool.py
jiki-0.1.1.dist-info/licenses/LICENSE
jiki-0.1.1.dist-info/METADATA
jiki-0.1.1.dist-info/WHEEL
jiki-0.1.1.dist-info/top_level.txt
jiki-0.1.1.dist-info/RECORD
