Metadata-Version: 2.4
Name: jiki
Version: 0.1.1
Summary: A flexible LLM orchestration framework with tool calling capabilities via MCP protocol
Author: Teilo Millet (teilomillet)
Requires-Python: >=3.10
License-File: LICENSE
Requires-Dist: mcp
Requires-Dist: litellm
Requires-Dist: pytest
Requires-Dist: fastmcp>=2.1.1
Requires-Dist: jsonschema
Dynamic: license-file
